sigmoidNN/__init__.py
sigmoidNN/loader.py
sigmoidNN/network.py
sigmoidNN/data/mnist.pkl.gz
sigmoidNN-0.11.dist-info/LICENCE
sigmoidNN-0.11.dist-info/METADATA
sigmoidNN-0.11.dist-info/WHEEL
sigmoidNN-0.11.dist-info/top_level.txt
sigmoidNN-0.11.dist-info/RECORD
