Metadata-Version: 2.2
Name: sigmoidNN
Version: 0.11
Summary: sigmoid neural network library
Home-page: https://github.com/Anas-github-Acc/SigmoidNN-package
Author: anas
Author-email: anas.ahamad955@gmail.com
Classifier: Programming Language :: Python :: 3
Classifier: License :: OSI Approved :: GNU General Public License v3 (GPLv3)
Classifier: Operating System :: OS Independent
Requires-Python: >=3.6
License-File: LICENCE
Requires-Dist: numpy
Dynamic: author
Dynamic: author-email
Dynamic: classifier
Dynamic: description
Dynamic: description-content-type
Dynamic: home-page
Dynamic: requires-dist
Dynamic: requires-python
Dynamic: summary
